LICENSE.md
LICENSE_RU.md
README.md
README_RU.md
examples.ipynb
examples_ru.ipynb
requirements.txt
setup.cfg
setup.py
clickhttp/__init__.py
clickhttp/check_conn.py
clickhttp/connection.py
clickhttp/create_temp.py
clickhttp/dtypes.py
clickhttp/errors.py
clickhttp/frame.py
clickhttp/insert.py
clickhttp/json_type.py
clickhttp/log.py
clickhttp/multiquery.py
clickhttp/read.py
clickhttp/session.py
clickhttp/sql_formatter.py
clickhttp.egg-info/PKG-INFO
clickhttp.egg-info/SOURCES.txt
clickhttp.egg-info/dependency_links.txt
clickhttp.egg-info/not-zip-safe
clickhttp.egg-info/requires.txt
clickhttp.egg-info/top_level.txt