Metadata-Version: 2.1
Name: clickhttp
Version: 0.1.2
Summary: Working with Clickhouse Database via HTTP Protocol | Работа с БД Clickhouse по HTTP-протоколу
Home-page: https://github.com/0xMihalich/clickhttp
Author: 0xMihalich
Author-email: bayanmobile87@gmail.com
License-File: LICENSE.md
License-File: LICENSE_RU.md
License-File: README_RU.md
Requires-Dist: backports.zoneinfo==0.2.1; python_version < "3.9"
Requires-Dist: requests>=2.31.0
Requires-Dist: sqlparse
